multiwidth/__init__.py
multiwidth/multiwidth.py
multiwidth-1.0.1.dist-info/METADATA
multiwidth-1.0.1.dist-info/WHEEL
multiwidth-1.0.1.dist-info/LICENSE
multiwidth-1.0.1.dist-info/RECORD
