Metadata-Version: 2.1
Name: multiwidth
Version: 1.0.1
Summary: A package for reading and writing mixed width tables
Home-page: https://github.com/jfcarter2358/multiwidth
License: MIT
Keywords: data,table,multiwidth
Author: John Carter
Author-email: jfcarter2358@gmail.com
Requires-Python: >=3.9,<4.0
Classifier: License :: OSI Approved :: MIT License
Classifier: Programming Language :: Python :: 3
Classifier: Programming Language :: Python :: 3.9
Classifier: Programming Language :: Python :: 3.10
Classifier: Programming Language :: Python :: 3.11
Project-URL: Repository, https://github.com/jfcarter2358/multiwidth
